{
  "__inputs": [
    {
      "name": "DS_POSTGRESQL",
      "label": "PostgreSQL",
      "description": "",
      "type": "datasource",
      "pluginId": "postgres",
      "pluginName": "PostgreSQL"
    }
  ],
  "__elements": {},
  "__requires": [
    {
      "type": "panel",
      "id": "geomap",
      "name": "Geomap",
      "version": ""
    },
    {
      "type": "grafana",
      "id": "grafana",
      "name": "Grafana",
      "version": "10.1.2"
    },
    {
      "type": "datasource",
      "id": "postgres",
      "name": "PostgreSQL",
      "version": "1.0.0"
    },
    {
      "type": "panel",
      "id": "timeseries",
      "name": "Time series",
      "version": ""
    }
  ],
  "annotations": {
    "list": [
      {
        "builtIn": 1,
        "datasource": {
          "type": "grafana",
          "uid": "-- Grafana --"
        },
        "enable": true,
        "hide": true,
        "iconColor": "rgba(0, 211, 255, 1)",
        "name": "Annotations & Alerts",
        "type": "dashboard"
      }
    ]
  },
  "editable": true,
  "fiscalYearStartMonth": 0,
  "graphTooltip": 0,
  "id": null,
  "links": [],
  "liveNow": false,
  "panels": [
    {
      "datasource": {
        "type": "postgres",
        "uid": "${DS_POSTGRESQL}"
      },
      "description": "",
      "fieldConfig": {
        "defaults": {
          "color": {
            "mode": "thresholds"
          },
          "custom": {
            "hideFrom": {
              "legend": false,
              "tooltip": false,
              "viz": false
            }
          },
          "mappings": [],
          "thresholds": {
            "mode": "absolute",
            "steps": [
              {
                "color": "green",
                "value": null
              },
              {
                "color": "red",
                "value": 80
              }
            ]
          }
        },
        "overrides": []
      },
      "gridPos": {
        "h": 17,
        "w": 12,
        "x": 0,
        "y": 0
      },
      "id": 1,
      "options": {
        "basemap": {
          "config": {},
          "name": "Layer 0",
          "type": "default"
        },
        "controls": {
          "mouseWheelZoom": true,
          "showAttribution": false,
          "showDebug": false,
          "showMeasure": false,
          "showScale": false,
          "showZoom": true
        },
        "layers": [
          {
            "config": {
              "showLegend": false,
              "style": {
                "color": {
                  "fixed": "#37872D"
                },
                "opacity": 0.3,
                "rotation": {
                  "fixed": 0,
                  "max": 360,
                  "min": -360,
                  "mode": "mod"
                },
                "size": {
                  "field": "baro_altitude",
                  "fixed": 5,
                  "max": 12,
                  "min": 2
                },
                "symbol": {
                  "fixed": "img/icons/marker/circle.svg",
                  "mode": "fixed"
                },
                "text": {
                  "field": "icao24",
                  "fixed": "",
                  "mode": "fixed"
                },
                "textConfig": {
                  "fontSize": 12,
                  "offsetX": 0,
                  "offsetY": 0,
                  "textAlign": "center",
                  "textBaseline": "middle"
                }
              }
            },
            "location": {
              "mode": "auto"
            },
            "name": "Layer 1",
            "tooltip": false,
            "type": "markers"
          }
        ],
        "tooltip": {
          "mode": "details"
        },
        "view": {
          "allLayers": true,
          "id": "fit",
          "lat": 0,
          "lon": 0,
          "padding": 100,
          "zoom": 15
        }
      },
      "pluginVersion": "10.1.2",
      "targets": [
        {
          "datasource": {
            "type": "postgres",
            "uid": "${DS_POSTGRESQL}"
          },
          "editorMode": "code",
          "format": "table",
          "rawQuery": true,
          "rawSql": "SELECT latitude, longitude, baro_altitude\r\nFROM aeronefs\r\nWHERE icao24 = '$var_icao24' \r\n  AND time_position >= TO_TIMESTAMP($__timeFrom(), 'YYYY-MM-DD\"T\"HH24:MI:SS.USSTZD')AT TIME ZONE 'UTC' + INTERVAL '4 hours'\r\n  AND time_position <= TO_TIMESTAMP($__timeTo(), 'YYYY-MM-DD\"T\"HH24:MI:SS.USSTZD')AT TIME ZONE 'UTC' + INTERVAL '4 hours'\r\n\r\n",
          "refId": "A",
          "sql": {
            "columns": [
              {
                "parameters": [
                  {
                    "name": "latitude",
                    "type": "functionParameter"
                  }
                ],
                "type": "function"
              }
            ],
            "groupBy": [
              {
                "property": {
                  "type": "string"
                },
                "type": "groupBy"
              }
            ],
            "limit": 50
          },
          "table": "aeronefs"
        }
      ],
      "title": "Suivi aéronef | icao24 : $var_icao24",
      "type": "geomap"
    },
    {
      "datasource": {
        "type": "postgres",
        "uid": "${DS_POSTGRESQL}"
      },
      "fieldConfig": {
        "defaults": {
          "color": {
            "mode": "palette-classic"
          },
          "custom": {
            "axisCenteredZero": false,
            "axisColorMode": "text",
            "axisLabel": "",
            "axisPlacement": "auto",
            "barAlignment": 0,
            "drawStyle": "line",
            "fillOpacity": 0,
            "gradientMode": "none",
            "hideFrom": {
              "legend": false,
              "tooltip": false,
              "viz": false
            },
            "insertNulls": false,
            "lineInterpolation": "linear",
            "lineWidth": 1,
            "pointSize": 5,
            "scaleDistribution": {
              "type": "linear"
            },
            "showPoints": "auto",
            "spanNulls": false,
            "stacking": {
              "group": "A",
              "mode": "none"
            },
            "thresholdsStyle": {
              "mode": "off"
            }
          },
          "mappings": [],
          "thresholds": {
            "mode": "absolute",
            "steps": [
              {
                "color": "green",
                "value": null
              },
              {
                "color": "red",
                "value": 80
              }
            ]
          },
          "unit": "lengthm"
        },
        "overrides": []
      },
      "gridPos": {
        "h": 9,
        "w": 12,
        "x": 12,
        "y": 0
      },
      "id": 2,
      "options": {
        "legend": {
          "calcs": [],
          "displayMode": "list",
          "placement": "bottom",
          "showLegend": false
        },
        "tooltip": {
          "mode": "single",
          "sort": "none"
        }
      },
      "targets": [
        {
          "datasource": {
            "type": "postgres",
            "uid": "${DS_POSTGRESQL}"
          },
          "editorMode": "code",
          "format": "table",
          "rawQuery": true,
          "rawSql": "select baro_altitude, time_position AT TIME ZONE 'Europe/Paris' AS time_position\r\nfrom aeronefs\r\nwhere icao24 = '$var_icao24'",
          "refId": "A",
          "sql": {
            "columns": [
              {
                "parameters": [],
                "type": "function"
              }
            ],
            "groupBy": [
              {
                "property": {
                  "type": "string"
                },
                "type": "groupBy"
              }
            ],
            "limit": 50
          }
        }
      ],
      "title": "Altitude barométrique en fonction du temps ",
      "transformations": [],
      "type": "timeseries"
    },
    {
      "datasource": {
        "type": "postgres",
        "uid": "${DS_POSTGRESQL}"
      },
      "fieldConfig": {
        "defaults": {
          "color": {
            "mode": "palette-classic"
          },
          "custom": {
            "axisCenteredZero": false,
            "axisColorMode": "text",
            "axisLabel": "",
            "axisPlacement": "auto",
            "barAlignment": 0,
            "drawStyle": "line",
            "fillOpacity": 0,
            "gradientMode": "none",
            "hideFrom": {
              "legend": false,
              "tooltip": false,
              "viz": false
            },
            "insertNulls": false,
            "lineInterpolation": "linear",
            "lineWidth": 1,
            "pointSize": 5,
            "scaleDistribution": {
              "type": "linear"
            },
            "showPoints": "auto",
            "spanNulls": false,
            "stacking": {
              "group": "A",
              "mode": "none"
            },
            "thresholdsStyle": {
              "mode": "off"
            }
          },
          "mappings": [],
          "thresholds": {
            "mode": "absolute",
            "steps": [
              {
                "color": "green",
                "value": null
              },
              {
                "color": "red",
                "value": 80
              }
            ]
          },
          "unit": "velocityms"
        },
        "overrides": []
      },
      "gridPos": {
        "h": 8,
        "w": 12,
        "x": 12,
        "y": 9
      },
      "id": 3,
      "options": {
        "legend": {
          "calcs": [],
          "displayMode": "list",
          "placement": "bottom",
          "showLegend": false
        },
        "timezone": [
          "browser"
        ],
        "tooltip": {
          "mode": "single",
          "sort": "none"
        }
      },
      "targets": [
        {
          "datasource": {
            "type": "postgres",
            "uid": "${DS_POSTGRESQL}"
          },
          "editorMode": "code",
          "format": "table",
          "rawQuery": true,
          "rawSql": "select velocity, time_position AT TIME ZONE 'Europe/Paris' AS time_position\r\nfrom aeronefs\r\nwhere icao24 = '$var_icao24'",
          "refId": "A",
          "sql": {
            "columns": [
              {
                "parameters": [],
                "type": "function"
              }
            ],
            "groupBy": [
              {
                "property": {
                  "type": "string"
                },
                "type": "groupBy"
              }
            ],
            "limit": 50
          }
        }
      ],
      "title": "Vitesse en m/s en fonction du temps ",
      "type": "timeseries"
    }
  ],
  "refresh": "30s",
  "schemaVersion": 38,
  "style": "dark",
  "tags": [],
  "templating": {
    "list": [
      {
        "current": {},
        "datasource": {
          "type": "postgres",
          "uid": "${DS_POSTGRESQL}"
        },
        "definition": "select distinct(icao24)\nfrom aeronefs",
        "hide": 0,
        "includeAll": false,
        "label": "icao24",
        "multi": false,
        "name": "var_icao24",
        "options": [],
        "query": "select distinct(icao24)\nfrom aeronefs",
        "refresh": 2,
        "regex": "",
        "skipUrlSync": false,
        "sort": 0,
        "type": "query"
      }
    ]
  },
  "time": {
    "from": "now-6h",
    "to": "now"
  },
  "timepicker": {},
  "timezone": "",
  "title": "Suivi aéronef",
  "uid": "c7bdd164-8356-47b1-93dc-6543e1160b0e",
  "version": 7,
  "weekStart": ""
}